{
    "business_id": "r5Ka92j1QFklGABmJKD03Q",
    "name": "Imperial Wok",
    "address": "1883 W Market St",
    "city": "Akron",
    "state": "OH",
    "postal_code": "44313",
    "latitude": 41.1127402,
    "longitude": -81.5756281,
    "stars": 3.5,
    "review_count": 31,
    "is_open": 1,
    "attributes": {
        "RestaurantsGoodForGroups": "True",
        "Alcohol": "u'none'",
        "WiFi": "u'no'",
        "RestaurantsTakeOut": "True",
        "Ambience": "{'romantic': False, 'intimate': False, 'classy': False, 'hipster': False, 'divey': False, 'touristy': False, 'trendy': False, 'upscale': False, 'casual': False}",
        "GoodForKids": "True",
        "OutdoorSeating": "False",
        "RestaurantsAttire": "u'casual'",
        "BusinessAcceptsCreditCards": "True",
        "RestaurantsPriceRange2": "1",
        "NoiseLevel": "u'average'",
        "BusinessParking": "{'garage': False, 'street': False, 'validated': False, 'lot': False, 'valet': False}",
        "BikeParking": "False",
        "HasTV": "True",
        "RestaurantsDelivery": "True",
        "RestaurantsReservations": "False"
    },
    "categories": "Asian Fusion, Chinese, Buffets, Restaurants",
    "hours": {
        "Monday": "10:0-22:0",
        "Tuesday": "10:0-22:0",
        "Wednesday": "10:0-22:0",
        "Thursday": "10:0-22:0",
        "Friday": "11:0-23:0",
        "Saturday": "11:0-23:0",
        "Sunday": "12:0-22:0"
    }
}