{
    "business_id": "VGKq16vCdPPHMoryy6XTHg",
    "name": "Natt Spil",
    "address": "211 King St",
    "city": "Madison",
    "state": "WI",
    "postal_code": "53703",
    "latitude": 43.0745755344,
    "longitude": -89.3797444136,
    "stars": 4.0,
    "review_count": 192,
    "is_open": 1,
    "attributes": {
        "BikeParking": "True",
        "RestaurantsGoodForGroups": "True",
        "RestaurantsReservations": "False",
        "BusinessAcceptsCreditCards": "False",
        "RestaurantsTakeOut": "False",
        "OutdoorSeating": "True",
        "RestaurantsPriceRange2": "2",
        "WiFi": "u'no'",
        "NoiseLevel": "u'average'",
        "Alcohol": "'full_bar'",
        "GoodForKids": "False",
        "RestaurantsDelivery": "False",
        "RestaurantsAttire": "'casual'",
        "BusinessParking": "{'garage': False, 'street': True, 'validated': False, 'lot': False, 'valet': False}",
        "Music": "{'dj': True, 'background_music': False, 'no_music': False, 'jukebox': False, 'live': False, 'video': False, 'karaoke': False}",
        "BYOBCorkage": "'no'",
        "Caters": "False",
        "GoodForMeal": "{'dessert': False, 'latenight': True, 'lunch': False, 'dinner': True, 'brunch': False, 'breakfast': False}",
        "CoatCheck": "False",
        "GoodForDancing": "False",
        "HappyHour": "True",
        "HasTV": "False",
        "Ambience": "{'touristy': False, 'hipster': True, 'romantic': False, 'divey': False, 'intimate': True, 'trendy': False, 'upscale': False, 'classy': True, 'casual': False}",
        "BestNights": "{'monday': True, 'tuesday': False, 'friday': True, 'wednesday': False, 'thursday': False, 'sunday': False, 'saturday': True}"
    },
    "categories": "Burgers, Bars, Dim Sum, Pizza, Chinese, Tapas/Small Plates, Nightlife, Restaurants",
    "hours": {
        "Monday": "17:0-2:0",
        "Tuesday": "17:0-2:0",
        "Wednesday": "17:0-2:0",
        "Thursday": "17:0-2:0",
        "Friday": "17:0-2:0",
        "Saturday": "17:0-2:0",
        "Sunday": "10:0-2:0"
    }
}