{
    "business_id": "xULATz2siGXOPia614mg2A",
    "name": "Lulu's Noodles",
    "address": "400 S Craig St",
    "city": "Pittsburgh",
    "state": "PA",
    "postal_code": "15213",
    "latitude": 40.445131,
    "longitude": -79.9490568,
    "stars": 3.0,
    "review_count": 424,
    "is_open": 1,
    "attributes": {
        "RestaurantsDelivery": "True",
        "HasTV": "False",
        "RestaurantsGoodForGroups": "True",
        "WiFi": "u'no'",
        "RestaurantsPriceRange2": "1",
        "Caters": "True",
        "BYOBCorkage": "'yes_free'",
        "Corkage": "False",
        "GoodForKids": "True",
        "RestaurantsReservations": "False",
        "BusinessAcceptsCreditCards": "True",
        "BusinessParking": "{'garage': False, 'street': True, 'validated': False, 'lot': False, 'valet': False}",
        "BikeParking": "True",
        "Alcohol": "'none'",
        "RestaurantsTakeOut": "True",
        "RestaurantsAttire": "'casual'",
        "NoiseLevel": "u'average'",
        "Ambience": "{'touristy': False, 'hipster': False, 'romantic': False, 'divey': False, 'intimate': False, 'trendy': False, 'upscale': False, 'classy': True, 'casual': True}",
        "OutdoorSeating": "False",
        "GoodForMeal": "{'dessert': False, 'latenight': False, 'lunch': True, 'dinner': True, 'brunch': False, 'breakfast': False}",
        "DogsAllowed": "False"
    },
    "categories": "Chinese, Restaurants, Pan Asian, Vegetarian, Korean, Noodles, Japanese",
    "hours": {
        "Monday": "11:0-21:0",
        "Tuesday": "11:0-21:0",
        "Wednesday": "11:0-21:0",
        "Thursday": "11:0-21:0",
        "Friday": "11:0-21:0",
        "Saturday": "11:0-21:0"
    }
}